{
  "cnf": {
    "common": {
      "action": {
          "add": "追加",
          "edit": "編集",
          "delete": "削除",
          "update": "更新",
          "save": "保存"
      }
    },
    "nav-title": {
        "clusters": "クラスタ",
        "dashboard": "ダッシュボード"
    },
    "clusters-list": {
        "title": "クラウド シリーズ ファイアウォール",
        "search-placeholder": "クラスタの検索",
        "add": "ファイアウォールの追加",
        "name": "名前",
        "status": "状態",
        "description": "説明",
        "license": "ライセンス",
        "type": "種類",
        "features": "機能",
        "manage": "管理",
        "feature": {
          "firewall":  "ファイアウォール",
          "waf": "WAF",
          "ips": "IPS"
        },
        "registration-status": {
          "waiting-for-deployment": "導入待機中",
          "awaiting-approval": "承認を待機中",
          "approved": "承認済み"
        },
        "installation-type": {
          "aws": "Amazon EKS",
          "on-prem": "オンプレミス"
        }
    },
    "add-cluster": {
      "cluster-name": "クラスタ名",
      "cluster-type":  "Kubernetes のインストールの種類",
      "cluster-description": "説明",
      "cluster-labels":  "ラベル",
      "cluster-services": "サービスのリスト",
      "cluster-installation-heading": "インストールの手順",
      "type-place-holder": "種類の選択",
      "action": "アクション",
      "type": {
        "premises": "オンプレミスインストール",
        "aws": "Amazon EKS"
      },
      "nfoptions-place-holder": "CNI の選択",
      "nf-options": {
        "new-cni": "既存の CNI は導入されていません",
        "flannel": "既存の Flannel のテイクオーバーがインストールされています",
        "calico": "Calico CNI は既にインストールされています",
        "different": "別の CNI がインストールされています"
      },
      "wafoptions-place-holder": "イングレスコントローラーの選択",
      "waf-options": {
        "no-ingress": "イングレスコントローラーはインストールされていません",
        "curifence": "Curifence は既にインストールされています",
        "traefik": "Traefik は既にインストールされています",
        "nginx": "NGINX は既にインストールされています",
        "different": "既に別のプロキシがインストールされています"
      },
      "services": {
        "network-firewall": "ネットワークファイアウォール",
        "waf": "Web アプリケーション ファイアウォール",
        "ip": "IPS (侵入防御)",
        "nf-label": "Kubernetes 用の Zero Trust ファイアウォールルール",
        "waf-label": "Web アプリケーションを安全に公開・保護します",
        "ip-label": "NGFW によるイングレス/エグレストラフィックの保護"
      },
      "btn-label": "導入の準備ができました",
      "cluster-name-error": "クラスタ名は 100文字を超えてはいけません。",
      "name-pattern-error": "クラスタ名に無効な文字が含まれています。",
      "cluster-description-error": "説明は、最大半角 250文字まで入力可能です。",
      "not-slected-cni": "CNI が選択されていません。現在の CNI を選択して続行してください。",
      "require-cni": "Cloud Series Firewall では、前提条件として CNI をインストール済みである必要があります。公式サイトから Calico CNI をインストールすることを推奨します。",
      "not-selected-ingress": "イングレスコントローラーが選択されていません。続行するには、イングレスコントローラーを選択するか、WAF 機能の選択を解除してください。",
      "not-supported-ingress": "WAF でサポートされていない既存のイングレスコントローラーが選択されました。WAF を使用するに合は、既存のイングレスコントローラーをクラスタから削除するか、WAF の選択を解除する必要があります。"
    }
  }
}
