{
  "shared.test": "test",
  "report.export.delete.modal-body": "Alle ausgewählten Exporte Löschen?",
  "report.export.delete.modal-header": "Exporte Löschen",
  "report.delete.label": "Löschen",
  "report.dialog.cancel": "Abbrechen",
  "report.dialog.confirm": "Bestätigen",
  "report.save.error-code.definitionIdNotFound": "Diese Berichtsdefinition wurde nicht gefunden",
  "report.save.error-code.deliveryType.isRequired": "Zustellungsart ist erforderlich",
  "report.save.error-code.format.isRequired": "Format des Berichts ist erforderlich",
  "report.save.error-code.frequency.isRequired": "Berichtshäufigkeit ist erforderlich",
  "report.save.error-code.general": "Ein Fehler ist aufgetreten: {{ message }}",
  "report.save.error-code.invalidFrequencyTimerangeCombination": "Ungültige Kombination aus Häufigkeit und Zeitspanne",
  "report.save.error-code.noRecurringScheduleFound": "Es wurde kein wiederkehrender Zeitplan gefunden",
  "report.save.error-code.reportIdNotFound": "Diese Berichtsdefinition wurde nicht gefunden",
  "report.save.error-code.reportLimitExceeded": "Warnung: Ihr Konto hat die maximale Anzahl gespeicherter Berichte erreicht. Wenn Sie neue Berichte erstellen möchten, löschen Sie zuerst nicht mehr verwendete Berichte.",
  "report.save.error-code.reportNameNotUnique": "Name der Berichtsdefinition ist nicht eindeutig",
  "report.save.error-code.reportNotFound": "Diese Berichtsdefinition wurde nicht gefunden",
  "report.save.error-code.scheduleNotFound": "Zeitplan wurde nicht gefunden",
  "report.save.error-code.timerangeDurationInvalid": "Ungültige Zeitspanne angegeben",
  "report.generate.modal.header": "Export",
  "report.generate.modal.generate": "Export",
  "report.generate.modal.save-and-generate": "Speichern und exportieren",
  "report.settings.until-i-cancel": "Bis ich abbreche",
  "report.settings.pii-disclaimer": "E-Mail-Anhänge können nicht verschlüsselt werden und werden daher nicht für Berichte empfohlen, die personenbezogene Daten (PII) enthalten. Aktivieren Sie das Kontrollkästchen, um zu bestätigen, dass Sie alles verstanden haben und fortfahren wollen.",
  "shared.endpoint-state.devices-table.column._dynamic_.id": "ID",
  "shared.endpoint-state.devices-table.column._dynamic_.tenantId": "ID des Mandanten ",
  "shared.endpoint-state.devices-table.column._dynamic_.hostname": "Name",
  "shared.endpoint-state.devices-table.column._dynamic_.os": "OS",
  "shared.endpoint-state.devices-table.column._dynamic_.osName": "Betriebssystem",
  "shared.endpoint-state.devices-table.column._dynamic_.type": "Typ",
  "shared.endpoint-state.devices-table.column._dynamic_.ipv4Addresses": "IPv4",
  "shared.endpoint-state.devices-table.column._dynamic_.ipv6Addresses": "IPv6",
  "shared.endpoint-state.devices-table.column._dynamic_.macAddresses": "MAC-Adressen",
  "shared.endpoint-state.devices-table.column._dynamic_.associatedLogin": "Zugehörige Anmeldung",
  "shared.endpoint-state.devices-table.column._dynamic_.associatedLoginName": "Letzter Benutzer",
  "shared.endpoint-state.devices-table.column._dynamic_.tamperProtectionEnabled": "Manipulationsschutz aktiviert",
  "shared.endpoint-state.devices-table.column._dynamic_.assignedProducts": "Zugewiesene Produkte",
  "shared.endpoint-state.devices-table.column._dynamic_.lastSeenAt": "Zuletzt gesehen bei",
  "shared.endpoint-state.devices-table.column._dynamic_.overallHealthStatus": "Allgemeiner Systemzustand",
  "shared.endpoint-state.devices-table.column._dynamic_.deviceGroupName": "Gruppe",
  "shared.endpoint-state.devices-table.device-type._dynamic_.computer": "Computer",
  "shared.endpoint-state.devices-table.device-type._dynamic_.server": "Server",
  "shared.endpoint-state.devices-table.device-type._dynamic_.securityVm": "VM-Sicherheitssystem"
}

