{
  "global.menu.manage-dashboard-list.title": "Gérer les tableaux de bord",
  "global.menu.manage-dashboard-list.description": "Gérer tous vos tableaux de bord",
  "tag-management.cancel": "Annuler",
  "tag-management.save": "Enregistrer",
  "tag-management.confirm": "Confirmer",
  "tag-management.create.add.tag.value": "Ajouter une valeur de balise",
  "tag-management.create.add.tag.key": "Nom de balise de la clé",
  "tag-management.create.title": "Créer une nouvelle balise",
  "tag-management.create.add.symbol": "+",
  "tag-management.create.tag.values": "Valeurs de la clé",
  "tag-management.create.tag.required": "Obligatoire",
  "tag-management.create.tag.invalid": "Valeur non valide",
  "tag-management.create.tag.value.delete": "Supprimer la valeur",
  "tag-management.create.tag.save.success": "Balise créée",
  "tag-management.create.tag.value.save.success": "Valeurs de balise mises à jour",
  "tag-management.success.toast.label": "Succès",
  "tag-management.create.tag.save.error": "Impossible de créer la balise",
  "tag-management.update.tag.values.error": "Impossible de mettre à jour les valeurs de balise",
  "tag-management.create.tag.save.duplicate.error": "Une balise du même nom existe déjà",
  "tag-management.update.tag.value.duplicate.error": "Une valeur du même nom existe déjà",
  "tag-management.update.tag.values.some.duplicate.error": "Valeurs de balise non dupliquées ajoutées",
  "tag-management.update.tag.values.all.duplicate.error": "Erreur : les valeurs de balise existent déjà",
  "tag-management.error.toast.label": "Erreur",
  "tag-management.add.tag.value": "Ajouter une nouvelle valeur de balise",
  "tag-management.add.tag.values": "[{{key_name}}] -  Créer des valeurs de balise",
  "tag-management.tag.value": "Valeur de balise",
  "tag-management.tag.value.minimum.error": "Un caractère minimum est requis",
  "tag-management.update.value.tag.value": "Ajouter une autre valeur de balise",
  "tag-management.tag-management.title": "Gérer les balises",
  "tag-management.no.tags": "Vous n’avez pas encore de balises",
  "tag-management.maximum.values": "Le nombre maximum de valeurs a été atteint",
  "tag-management.maximum.tags": "Le nombre maximum de balises a été atteint",
  "tag-management.no.tags.add.message": "Cliquez sur Créer une nouvelle balise pour ajouter une balise",
  "tag-management.show.usage": "Afficher l’utilisation",
  "tag-management.hide.usage": "Masquer l’utilisation",
  "tag-management.no.of.values": "({{count}} valeurs)",
  "tag-management.no.of.assigned": "({{count}} assignées)",
  "tag-management.no.of.values.in.use": "({{count}} valeurs utilisées)",
  "custom.dashboard.details.title": "Détails du tableau de bord",
  "custom.dashboard.details.name": "Nom",
  "custom.dashboard.duplicate.name": "Ce nom existe déjà",
  "custom-dashboard.validation.text": "Ne doit pas dépasser {{count}}",
  "custom.dashboard.details.desc": "Description",
  "custom.dashboard.details.widgets.title": "Widgets",
  "custom.dashboard.details.widgets.new": "Nouveau",
  "mange-dashboard.delete.dialog.header":"Supprimer le tableau de bord",
  "mange-dashboard.delete.dialog.body-a":"Supprimer le tableau de bord {{dashboard_name}}.",
  "mange-dashboard.delete.dialog.body-b":"Cette opération est irréversible.",
  "mange-dashboard.delete.dialog.delete-button":"Supprimer le tableau de bord",
  "mange-dashboard.delete.dialog.cancel-button":"Annuler",
  "mange-dashboard.delete.dialog.success.toast":"Tableau de bord supprimé",
  "mange-dashboard.delete.dialog.error.toast":"Impossible de supprimer le tableau de bord. Veuillez réessayer ultérieurement.",
  "mange-dashboard.remove.dialog.header":"Retirer le tableau de bord",
  "mange-dashboard.remove.dialog.body-a":"Retirer le tableau de bord {{dashboard_name}} de la liste.",
  "mange-dashboard.remove.dialog.body-b":"Vous pouvez le rajouter ultérieurement.",
  "mange-dashboard.remove.dialog.remove-button":"Retirer le tableau de bord",
  "mange-dashboard.remove.dialog.success.toast":"Tableau de bord retiré de votre liste",
  "mange-dashboard.remove.dialog.error.toast":"Impossible de retirer le tableau de bord. Veuillez réessayer ultérieurement.",
  "mange-dashboard.list.table.name.header":"Nom",
  "mange-dashboard.list.table.description.header":"Description",
  "mange-dashboard.list.table.set-default.header":"Définir par défaut",
  "mange-dashboard.list.table.unpin.tooltip":"Détacher le tableau de bord",
  "mange-dashboard.list.table.pin.tooltip":"Épingler le tableau de bord",
  "mange-dashboard.list.table.default-pinned.tooltip":"Impossible de détacher le tableau de bord par défaut",
  "mange-dashboard.list.table.default-removed.tooltip":"Impossible de supprimer le tableau de bord par défaut",
  "mange-dashboard.list.table.remove.tooltip":"Retirer de la liste",
  "mange-dashboard.list.table.delete.tooltip":"Supprimer",
  "mange-dashboard.list.pin-dashboard.toast":"Tableau de bord épinglé",
  "mange-dashboard.list.unpin-dashboard.toast":"Tableau de bord détaché",
  "mange-dashboard.list.default-dashboard-changed.toast":"Tableau de bord par défaut mis à jour",
  "mange-dashboard.list.dashboard-load-fail.toast":"Impossible de charger les tableaux de bord.",
  "mange-dashboard.list.table.author.header":"Auteur",
  "mange-dashboard.list.button.create-new":"Créer",
  "mange-dashboard.list.button.create-dashboard.header":"Créer un tableau de bord",
  "mange-dashboard.list.button.clone-dashboard.header":"Cloner le tableau de bord",
  "mange-dashboard.list.button.find-dashboards":"Trouver des tableaux de bord",
  "mange-dashboard.list.button.edit":"Modifier",
  "mange-dashboard.list.button.delete":"Supprimer",
  "mange-dashboard.list.button.clone":"Cloner",
  "mange-dashboard.list.button.next":"Suivant",
  "mange-dashboard.list.button.cancel":"Annuler",
  "mange-dashboard.list.clone.text.copy":"Copier",
  "manage-dashboards.breadcrumbs.title": "Tableaux de bord",
  "mange-dashboard.list.no.description":"Aucune description",
  "manage-dashboards.pin-icon-tooltip": "Épingle un tableau de bord pour l’afficher dans le menu Tableaux de bord",
  "manage-dashboards.author-sophos-icon-tooltip": "Tableau de bord Sophos",
  "manage-dashboards.find-dashboards.description": "Retrouvez ici les tableaux de bord créés par Sophos",
  "tag-management.tag.delete": "Supprimer",
  "tag-management.edit.tag.color": "Modifier la couleur de la balise",
  "global.meganav.menu.group.pinned": "ÉPINGLÉ",
  "tag-management.tag.sort.label": "Trier",
  "tag-management.tag.sort.asc": "Par ordre alphabétique de A à Z",
  "tag-management.tag.sort.desc":"Par ordre alphabétique inversé de Z à A",
  "tag-management.tag.values.sort.asc": "Par ordre alphabétique de A à Z",
  "tag-management.tag.values.sort.desc": "Par ordre alphabétique inversé de Z à A",
  "custom-dashboard.actions.saving": "Enregistrement...",
  "custom-dashboard.actions.saved": "Modifications enregistrées",
  "custom-dashboard.actions.product": "Produit",
  "custom-dashboard.actions.all-product": "Tous les produits",
  "custom-dashboard.actions.roles": "Rôles",
  "custom-dashboard.actions.all-roles": "Tous les rôles",
  "custom-dashboard.actions.data": "Données",
  "custom-dashboard.actions.widget-type": "Type de widget",
  "custom-dashboard.actions.sort": "Trier",
  "custom-dashboard.actions.filter": "Filtrer"
}
