{
  "cloud-switch": {
    "common": {
      "main-dashboard-breadcrumb-text": "Visão Geral",
      "button": {
        "register": "Registrar",
        "cancel": "Cancelar",
        "yes": "Sim",
        "no": "Não",
        "save": "Salvar",
        "bugs": "Erros",
        "apply": "Aplicar"
      },
      "status": {
        "registering": "Aguardando conexão",
        "connected": "Conectado",
        "registered": "Registrado",
        "unregistered": "Limite de tempo de registro expirou",
        "disconnected": "Desconectado",
        "suspended": "Suspenso"
      },
      "form": {
        "name": "Nome",
        "description": "Descrição"
      },
      "error": "Erro",
      "success": "Bem-sucedido",
      "warn": "Aviso",
      "used": "Usado",
      "waitingForData": "Aguardando dados...",
      "problemLoadingData": "Problema no carregamento de dados",
      "areYouSure": "Tem certeza de que deseja continuar?"
    },
    "dashboard": {
      "menu-title": "Painel",
      "page-title": "Switches - Painel",
      "breadcrumb-text": "Painel de Switches",
      "message": {
        "no-switches-registered": "Nenhum switch disponível"
      },
      "button": {
        "add-switch": "Adicionar switches"
      }
    },
    "switches": {
      "list": {
        "menu-title": "Switches",
        "page-title": "Switches",
        "breadcrumb-text": "Switches",
        "title": "Nuvem - Switches",
        "toggleColumnsTitle": "Alternar colunas",
        "removeDialogTitle": "Remover switch {{switchSerial}}",
        "retryDialogTitle": "Tentar registro novamente",
        "txtbox": {
          "search-placeholder": "Pesquisar switch"
        },
        "action-menu": {
          "retry": "Tentar registro novamente",
          "removeFromCentral": "Remover do Sophos Central"
        },
        "button": {
          "auto-refresh": "Autoatualizar",
          "add-template": "Adicionar modelo"
        },
        "table-headers": {
          "name": "Nome",
          "alerts": "Alertas",
          "managementStatus": "Status",
          "version": "Versão",
          "location": "Localização",
          "ports": "Portas",
          "connections": "Conexões",
          "vlans": "VLANs",
          "untagged-vlans": "VLANs sem tags",
          "ip-address": "Nome de host / Endereço IP",
          "tags": "Tags",
          "model": "Modelo",
          "serial-number": "Número de série",
          "template-overridden": "Modelo substituído?"
        },
        "upgrade": {
          "update-available": "Há novas atualizações de firmware disponíveis.",
          "upgrade-message": "Esses upgrades podem ser agendados ou aplicados imediatamente.",
          "schedule-upgrade": "Agendar upgrade",
          "schedule": "Cronograma",
          "manage-schedule-dialog-title": "Gerenciar upgrades de firmware",
          "upgrade-schedule-dialog-title": "Agendar upgrades de firmware",
          "dialog-heading": "Gerenciar agendamentos e upgrades de switch",
          "schedule-info-message": "Escolha quando atualizar os switches selecionados",
          "update-now": "Atualizar agora",
          "custom": "Personalizado",
          "scheduled-success-message": "A atualização de firmware foi agendada",
          "update-cancel-message": "A atualização de firmware foi cancelada",
          "cancel-upgrade": "Cancelar upgrade",
          "table": {
            "name": "Nome",
            "version": "Versão",
            "update-to": "Atualizar para",
            "currently-scheduled-upgrades": "Upgrades agendados no momento",
            "release-notes": "Notas de versão",
            "edit": "Editar",
            "selected": "Selecionado(s)"
          }
        },
        "add-template": {
          "dialog-title": "Adicionar um modelo",
          "name-max-length": "O nome deve ter um máximo de 30 caracteres.",
          "description": "Descrição",
          "input-name-required-message": "É necessário um nome de modelo",
          "template-description": "A descrição deve ter um máximo de 128 caracteres.",
          "available-switches": "Switches disponíveis",
          "assigned-switches": "Switches atribuídos",
          "sync-switches-checkbox-text": "Sincronizar os switches com a configuração de modelo inicial"
        },
        "message": {
          "remove-success": "O switch {{switchSerial}} foi removido do Sophos Central.",
          "remove-failed": "Não foi possível remover o switch do Sophos Central.",
          "retry-success": "O registro do switch {{switchSerial}} foi disparado novamente.",
          "retry-failed": "Não foi possível disparar registro.",
          "add-template-success": "O modelo foi adicionado"
        },
        "groupInfoText": {
          "what": "O que é um modelo?",
          "information": "Um modelo de switch é um modelo de configuração de switch virtual que pode ser aplicado a um ou mais switches. É possível mover um switch para dentro de um modelo ou para fora dele, conforme necessário. Contanto que o switch esteja sob um modelo, as configurações feitas no nível do modelo serão sincronizadas automaticamente com os switches.",
          "note": "Observe que a substituição da configuração no nível do switch terá precedência durante a avaliação de configurações conflitantes de um switch sob o modelo."
        }
      }
    },
    "register": {
      "modal": {
        "title": "Adicionar switches",
        "step-1": {
          "title": "Passo 1",
          "description": "Conecte os seus switches à rede de modo que possam alcançar a internet."
        },
        "step-2": {
          "title": "Passo 2",
          "description": "Encontre o número de série (S/N) nos switches. O número de série é a identidade do switch."
        },
        "step-3": {
          "title": "Passo 3",
          "description": "Insira os números de série dos switches para registrar. (Separados por vírgula)"
        },
        "checkbox": {
          "terms-and-conditions": "Eu concordo com os <a style=\"text-decoration:underline\" id=\"anchor-user-agreement\" href=\"https://www.sophos.com\" target=\"_blank\">Termos e Condições</a>",
          "auto-approve": "Aprove o dispositivo automaticamente assim que for estabelecida a conexão com o Sophos Central para registro",
          "auto-upgrade": "Atualize os switches automaticamente com a versão mais recente do software disponível, se não for necessária a reinicialização para o upgrade"
        },
        "body": {
          "line-1": "Certifique-se de que os switches estejam ativados durante o registro. O processo de registro sem toque ficará ativo por apenas 5 minutos.",
          "line-2": "Os switches registrados serão movidos para um modelo padrão, inicialmente.",
          "line-3": "Os switches serão atualizados automaticamente com a versão mais recente do software disponível, logo após o registro. Isso pode exigir a reinicialização do dispositivo."
        }
      },
      "message": {
        "already-reported": "Os switches com números de série {{ switches }} já estão registrados no Sophos Central.",
        "registration-error": "Não foi possível registrar os switches.",
        "switches-registered": "Os switches estão sendo registrados: conecte seus switches à rede.",
        "switch-serial-max-length": "O número de série não pode conter mais do que 15 caracteres.",
        "empty-switch-list-error": "Não há nenhum número de série válido."
      }
    }
  }
}