{
  "core.ago": "hace {{ timespan }}",
  "core.facet-filter.title": "Filtros",
  "core.facet-style-filter.clearall": "Restablecer valores predeterminados",
  "core.lastUpdated": "Última actualización: {{localizedDateTime}}",
  "core.sc-table-filter-bar.show-filters": "Mostrar filtros",
  "core.sc-table-filter-bar.hide-filters": "Ocultar filtros",
  "core.sc-pagination-display-info.loading": "Cargando...",
  "core.assign-selector.empty.message": "Esta página no tiene elementos",
  "core.assign-selector.total-selected": "{{ selected }} de {{ total }}",
  "core.calendar.today": "Hoy",
  "core.day-picker.label.sunday": "Dom",
  "core.day-picker.label.monday": "Lun",
  "core.day-picker.label.tuesday": "Mar",
  "core.day-picker.label.wednesday": "Mié",
  "core.day-picker.label.thursday": "Jue",
  "core.day-picker.label.friday": "Vie",
  "core.day-picker.label.saturday": "Sáb",
  "core.storefront.sample-page.breadcrumb": "Panel de control Vista general",
  "core.storefront.sample-page.breadcrumb-title": "Biblioteca de componentes de Angular 7",
  "core.storefront.sample-page.title": "Muestras de Storefront",
  "core.storefront.dropdown-tree.selected-item-message": "{{count}} elemento(s) seleccionado(s)",
  "core.storefront.dropdown-tree.deselect-all": "Desmarcar todo",
  "core.storefront.dropdown-tree.no-item-selected": "Seleccionar elementos",
  "core.storefront.dropdown-tree.search": "Buscar",
  "core.storefront.dropdown-tree.no-records": "No hay registros",
  "core.storefront.dropdown-tree.apply": "Aplicar",
  "core.storefront.pagination.selected": "Mostrando {{start}} - {{end}} de {{total}} / {{ selected }} seleccionado(s)",
  "core.units._dynamic_.b.second": "{{ value }} bit/s",
  "core.units._dynamic_.b.size": "{{ value }} B",
  "core.units._dynamic_.gb.second": "{{ value }} Gbit/s",
  "core.units._dynamic_.gb.size": "{{ value }} GB",
  "core.units._dynamic_.kb.second": "{{ value }} kbit/s",
  "core.units._dynamic_.kb.size": "{{ value }} kB",
  "core.units._dynamic_.mb.second": "{{ value }} Mbit/s",
  "core.units._dynamic_.mb.size": "{{ value }} MB",
  "core.units._dynamic_.tb.second": "{{ value }} Tbit/s",
  "core.units._dynamic_.tb.size": "{{ value }} TB",
  "core.units.b.second": "{{ value }} B/s",
  "core.units.bit.second": "{{ value }} bps",
  "core.units.bit.standalone": "Bits",
  "core.units.byte.standalone": "Bytes",
  "core.units.duration.days.short": "d",
  "core.units.duration.hours.short": "h",
  "core.units.duration.milliseconds.short": "ms",
  "core.units.duration.minutes.short": "m",
  "core.units.duration.months.short": "me",
  "core.units.duration.seconds.short": "s",
  "core.units.duration.years.short": "a",
  "core.units.gb.second": "{{ value }} GB/s",
  "core.units.gbit.second": "{{ value }} Gbps",
  "core.units.gb.standalone": "GB",
  "core.units.gbit.standalone": "Gb",
  "core.units.kb.second": "{{ value }} kB/s",
  "core.units.kbit.second": "{{ value }} Kbps",
  "core.units.kb.standalone": "KB",
  "core.units.kbit.standalone": "Kb",
  "core.units.mb.second": "{{ value }} MB/s",
  "core.units.mbit.second": "{{ value }} Mbps",
  "core.units.mb.standalone": "MB",
  "core.units.mbit.standalone": "Mb",
  "core.units.tb.second": "{{ value }} TB/s",
  "core.units.tbit.second": "{{ value }} Tbps",
  "core.units.tb.standalone": "TB",
  "core.color.label.white": "Blanco",
  "core.color.label.blue": "Azul",
  "core.color.label.purple": "Púrpura",
  "core.color.label.pink": "Rosa",
  "core.color.label.red": "Rojo",
  "core.color.label.orange": "Naranja",
  "core.color.label.yellow": "Amarillo",
  "core.color.label.green": "Verde",
  "core.color.label.brown": "Marrón",
  "core.color.label.black": "Negro",
  "core.color.label.custom": "Personalizada"
}
