{
  "core.facet-filter.title": "필터",
  "core.facet-style-filter.clearall": "모두 지우기",
  "core.pagination-left._dynamic_.range.no-select": "{{ total }}개 중에 {{ filtered }}개를 표시하는 중",
  "core.pagination-left._dynamic_.no-select": "을(를) 표시하는 중 {{ total }}",
  "core.pagination-left._dynamic_.range.select": "선택된{{ total }}/{{ selected }}개 중에 {{ filtered }}개를 표시하는 중",
  "core.sc-table-filter-bar.show-filters": "필터 표시",
  "core.sc-table-filter-bar.hide-filters": "필터 숨기기",
  "core.storefront.sample-page.breadcrumb": "개요 대시보드",
  "core.storefront.sample-page.breadcrumb-title": "Angular 7 구성 요소 라이브러리",
  "core.storefront.sample-page.title": "Storefront 샘플",
  "core.storefront.dropdown-tree.selected-item-message": "{{count}}개 항목 선택됨",
  "core.storefront.dropdown-tree.deselect-all": "모두 선택 취소",
  "core.storefront.dropdown-tree.no-item-selected": "항목 선택",
  "core.storefront.dropdown-tree.search": "검색",
  "core.storefront.dropdown-tree.no-records": "레코드 없음",
  "core.storefront.dropdown-tree.apply": "적용"
}
